cryosieve/ParticleDataset.py
cryosieve/__init__.py
cryosieve/__main__.py
cryosieve/core.py
cryosieve/cs_refine.py
cryosieve/cs_rhbfactor.py
cryosieve/kernels.py
cryosieve/sieve.py
cryosieve/utility.py
cryosieve-1.2.8.dist-info/AUTHORS
cryosieve-1.2.8.dist-info/LICENSE
cryosieve-1.2.8.dist-info/METADATA
cryosieve-1.2.8.dist-info/WHEEL
cryosieve-1.2.8.dist-info/entry_points.txt
cryosieve-1.2.8.dist-info/top_level.txt
cryosieve-1.2.8.dist-info/RECORD
