Metadata-Version: 2.1
Name: cryosieve
Version: 1.2.8
Summary: CryoSieve: a particle sorting and sieving algorithm for single particle analysis in cryo-EM
Author-email: Jianying Zhu <zhu-jy20@mails.tsinghua.edu.cn>, Qi Zhang <q-zhang20@mails.tsinghua.edu.cn>, Hui Zhang <zhanghui23@mails.tsinghua.edu.cn>, Zuoqiang Shi <zqshi@tsinghua.edu.cn>, Mingxu Hu <humingxu@smart.org.cn>, Chenglong Bao <clbao@tsinghua.edu.cn>
License: GNU GENERAL PUBLIC LICENSE
Project-URL: Homepage, https://github.com/mxhulab/cryosieve
Classifier: Programming Language :: Python :: 3
Classifier: License :: OSI Approved :: GNU General Public License v3 (GPLv3)
Classifier: Operating System :: OS Independent
Classifier: Environment :: GPU :: NVIDIA CUDA
Classifier: Topic :: Scientific/Engineering :: Image Processing
Requires-Python: >=3.7
License-File: LICENSE
License-File: AUTHORS
Requires-Dist: numpy >=1.18
Requires-Dist: mrcfile >=1.2
Requires-Dist: starfile <0.5,>=0.4.1
Requires-Dist: pandas <2.2
Requires-Dist: cupy >=10
Requires-Dist: torch >=1.10
